pilot/callback.py
pilot/definitions.py
pilot/exception.py
pilot/node.py
pilot/pilot.py
pilot/tests.py
pilot/__init__.py
pilot/__main__.py
pilot-0.0.8.dist-info/DESCRIPTION.rst
pilot-0.0.8.dist-info/METADATA
pilot-0.0.8.dist-info/metadata.json
pilot-0.0.8.dist-info/RECORD
pilot-0.0.8.dist-info/top_level.txt
pilot-0.0.8.dist-info/WHEEL
